payvo_sdk/__init__.py
payvo_sdk/client.py
payvo_sdk-0.1.0.dist-info/METADATA
payvo_sdk-0.1.0.dist-info/WHEEL
payvo_sdk-0.1.0.dist-info/top_level.txt
payvo_sdk-0.1.0.dist-info/RECORD
