Metadata-Version: 2.4
Name: payvo_sdk
Version: 0.1.0
Summary: Python SDK для работы с Payvo API
Home-page: https://github.com/erruqie/payvo_sdk
Author: erruqie
Author-email: clownl3ss@icloud.com
Classifier: Programming Language :: Python :: 3
Classifier: License :: OSI Approved :: MIT License
Classifier: Operating System :: OS Independent
Requires-Python: >=3.8
Requires-Dist: requests>=2.30.0
Dynamic: author
Dynamic: author-email
Dynamic: classifier
Dynamic: description
Dynamic: description-content-type
Dynamic: home-page
Dynamic: requires-dist
Dynamic: requires-python
Dynamic: summary
